pyerz/__init__.py
pyerz/pyerz.py
pyerz/template.docx
pyerz-1.0.2.dist-info/LICENSE.txt
pyerz-1.0.2.dist-info/METADATA
pyerz-1.0.2.dist-info/WHEEL
pyerz-1.0.2.dist-info/entry_points.txt
pyerz-1.0.2.dist-info/top_level.txt
pyerz-1.0.2.dist-info/RECORD
