Metadata-Version: 2.1
Name: pyerz
Version: 1.0.2
Summary: 易软著Python库
Home-page: UNKNOWN
Author: soultoolman
Author-email: soultoolman@gmail.com
License: MIT
Platform: UNKNOWN
Classifier: License :: OSI Approved :: MIT License
Classifier: Programming Language :: Python
Classifier: Programming Language :: Python :: 3
Classifier: Programming Language :: Python :: 3.6
Classifier: Programming Language :: Python :: Implementation :: CPython
Classifier: Programming Language :: Python :: Implementation :: PyPy
Classifier: Topic :: Scientific/Engineering :: Bio-Informatics
Requires-Python: >=3.6.0
Requires-Dist: click
Requires-Dist: scandir
Requires-Dist: python-docx
